reportify_sdk/__init__.py
reportify_sdk/agent.py
reportify_sdk/channels.py
reportify_sdk/chat.py
reportify_sdk/client.py
reportify_sdk/concepts.py
reportify_sdk/docs.py
reportify_sdk/exceptions.py
reportify_sdk/kb.py
reportify_sdk/quant.py
reportify_sdk/search.py
reportify_sdk/stock.py
reportify_sdk/timeline.py
reportify_sdk/user.py
reportify_sdk-0.3.2.dist-info/licenses/LICENSE
reportify_sdk-0.3.2.dist-info/METADATA
reportify_sdk-0.3.2.dist-info/WHEEL
reportify_sdk-0.3.2.dist-info/top_level.txt
reportify_sdk-0.3.2.dist-info/RECORD
