Metadata-Version: 2.4
Name: reportify-sdk
Version: 0.3.2
Summary: Python SDK for Reportify API - Financial data and document search
Author-email: Reportify <support@reportify.cn>
License-Expression: MIT
Project-URL: Homepage, https://reportify.cn
Project-URL: Documentation, https://docs.reportify.cn
Project-URL: Repository, https://github.com/reportify/reportify-sdk-python
Keywords: reportify,finance,stock,api,sdk
Classifier: Development Status :: 4 - Beta
Classifier: Intended Audience :: Developers
Classifier: Operating System :: OS Independent
Classifier: Programming Language :: Python :: 3
Classifier: Programming Language :: Python :: 3.9
Classifier: Programming Language :: Python :: 3.10
Classifier: Programming Language :: Python :: 3.11
Classifier: Programming Language :: Python :: 3.12
Classifier: Topic :: Software Development :: Libraries :: Python Modules
Requires-Python: >=3.9
License-File: LICENSE
Requires-Dist: httpx>=0.25.0
Requires-Dist: pandas>=2.0.0
Provides-Extra: dev
Requires-Dist: pytest>=7.0.0; extra == "dev"
Requires-Dist: pytest-asyncio>=0.21.0; extra == "dev"
Dynamic: license-file
